brutalpywebui/__init__.py
brutalpywebui/favicon.py
brutalpywebui/font.py
brutalpywebui/normalize_css.py
brutalpywebui/script.py
brutalpywebui/wrapper.py
brutalpywebui-0.1.0.dist-info/LICENSE
brutalpywebui-0.1.0.dist-info/LICENSE.jetbrainsmono.txt
brutalpywebui-0.1.0.dist-info/METADATA
brutalpywebui-0.1.0.dist-info/WHEEL
brutalpywebui-0.1.0.dist-info/RECORD
