Metadata-Version: 2.1
Name: brutalpywebui
Version: 0.1.0
Summary: 
Author: Zen
Author-email: zen@zenoverflow.com
Requires-Python: >=3.11,<4.0
Classifier: Programming Language :: Python :: 3
Classifier: Programming Language :: Python :: 3.11
Classifier: Programming Language :: Python :: 3.12
Requires-Dist: hypercorn (>=0.16.0,<0.17.0)
Requires-Dist: quart (>=0.19.4,<0.20.0)
